odoo/addons/helpdesk_mgmt_fieldservice_equipment/README.rst
odoo/addons/helpdesk_mgmt_fieldservice_equipment/__init__.py
odoo/addons/helpdesk_mgmt_fieldservice_equipment/__manifest__.py
odoo/addons/helpdesk_mgmt_fieldservice_equipment/i18n/helpdesk_mgmt_fieldservice_equipment.pot
odoo/addons/helpdesk_mgmt_fieldservice_equipment/models/__init__.py
odoo/addons/helpdesk_mgmt_fieldservice_equipment/models/fsm_equipment.py
odoo/addons/helpdesk_mgmt_fieldservice_equipment/models/helpdesk_ticket.py
odoo/addons/helpdesk_mgmt_fieldservice_equipment/readme/CONTRIBUTORS.md
odoo/addons/helpdesk_mgmt_fieldservice_equipment/readme/DESCRIPTION.md
odoo/addons/helpdesk_mgmt_fieldservice_equipment/static/description/icon.png
odoo/addons/helpdesk_mgmt_fieldservice_equipment/static/description/index.html
odoo/addons/helpdesk_mgmt_fieldservice_equipment/tests/__init__.py
odoo/addons/helpdesk_mgmt_fieldservice_equipment/tests/test_fsm_equipment.py
odoo/addons/helpdesk_mgmt_fieldservice_equipment/tests/test_helpdesk_ticket.py
odoo/addons/helpdesk_mgmt_fieldservice_equipment/views/helpdesk_ticket.xml
odoo_addon_helpdesk_mgmt_fieldservice_equipment-18.0.1.0.0.2.dist-info/METADATA
odoo_addon_helpdesk_mgmt_fieldservice_equipment-18.0.1.0.0.2.dist-info/WHEEL
odoo_addon_helpdesk_mgmt_fieldservice_equipment-18.0.1.0.0.2.dist-info/top_level.txt
odoo_addon_helpdesk_mgmt_fieldservice_equipment-18.0.1.0.0.2.dist-info/RECORD
